bplot/__init__.py
bplot/display.py
bplot/hist1d.py
bplot/plot1d.py
bplot/plot2d.py
bplot/scatter1d.py
bplot/test.py
bplot-0.3.0.dist-info/licenses/LICENSE
bplot-0.3.0.dist-info/METADATA
bplot-0.3.0.dist-info/WHEEL
bplot-0.3.0.dist-info/entry_points.txt
bplot-0.3.0.dist-info/top_level.txt
bplot-0.3.0.dist-info/RECORD
