Metadata-Version: 2.4
Name: bplot
Version: 0.3.0
Summary: bplot
Home-page: https://github.com/alessandrosebastianelli/bplot.git
Author: Alessandro Sebastianelli
Author-email: Alessandro Sebastianelli <alessandro.sebastianelli1995@gmail.com>
License: Copyright (c) 2023-2023 Alessandro Sebastianelli
Project-URL: Homepage, https://github.com/alessandrosebastianelli/bplot
Project-URL: Bug Tracker, https://github.com/alessandrosebastianelli/bplot/issues
Project-URL: How to contribute, https://github.com/alessandrosebastianelli/bplot/issues/1
Classifier: Programming Language :: Python :: 3
Classifier: License :: OSI Approved :: MIT License
Classifier: Operating System :: OS Independent
Requires-Python: >=3.10
License-File: LICENSE
Requires-Dist: numpy
Requires-Dist: matplotlib
Requires-Dist: pandas
Requires-Dist: pyosv
Dynamic: author
Dynamic: home-page
Dynamic: license-file
